data_structures_margo/__init__.py
data_structures_margo/avl_tree.py
data_structures_margo-0.1.1.dist-info/METADATA
data_structures_margo-0.1.1.dist-info/WHEEL
data_structures_margo-0.1.1.dist-info/RECORD
